nephyx-0.0.23.dist-info/METADATA
nephyx-0.0.23.dist-info/WHEEL
nephyx-0.0.23.dist-info/entry_points.txt
nephyx/__init__.py
nephyx/__main__.py
nephyx/auth/__init__.py
nephyx/cli/__init__.py
nephyx/cli/app.py
nephyx/cli/helper.py
nephyx/cli/postgres.py
nephyx/db/__init__.py
nephyx/db/manager.py
nephyx/db/model.py
nephyx/db/repository.py
nephyx/manage/__init__.py
nephyx/py.typed
nephyx/scheduled.py
nephyx/schema.py
nephyx/security/__init__.py
nephyx/security/auth.py
nephyx/settings.py
nephyx-0.0.23.dist-info/RECORD
