Metadata-Version: 2.1
Name: nephyx
Version: 0.0.23
Summary: nephyx bootstrap library for FastAPI applications
Author-Email: Sascha Lamp <sascha.lamp@lampware.de>
License: MIT
Requires-Python: >=3.12
Requires-Dist: sqlalchemy>=2.0.37
Requires-Dist: fastapi>=0.115.7
Requires-Dist: fastapi-utilities>=0.3.0
Requires-Dist: pydantic-settings>=2.8.0
Requires-Dist: typer>=0.15.1
Requires-Dist: psycopg[binary]>=3.2.5
Requires-Dist: uvicorn>=0.34.0
